nonebot_plugin_charpic-0.2.1.dist-info/METADATA
nonebot_plugin_charpic-0.2.1.dist-info/WHEEL
nonebot_plugin_charpic-0.2.1.dist-info/entry_points.txt
nonebot_plugin_charpic-0.2.1.dist-info/licenses/LICENSE
nonebot_plugin_charpic/__init__.py
nonebot_plugin_charpic/data_source.py
nonebot_plugin_charpic/depends.py
nonebot_plugin_charpic/font/consola.ttf
nonebot_plugin_charpic-0.2.1.dist-info/RECORD
