Metadata-Version: 2.1
Name: nonebot-plugin-charpic
Version: 0.2.1
Summary: Generate picture(or GIF) by characters
Author-Email: 1umine <a1628420979@163.com>
License: MIT
Requires-Python: >=3.10
Requires-Dist: Pillow>=9.0.0
Requires-Dist: httpx>=0.27.0
Requires-Dist: imageio<3.0,>=2.9.0
Requires-Dist: nonebot2<3.0,>=2.0
Requires-Dist: nonebot-plugin-alconna>=0.42.4
